fastenv/__init__.py
fastenv/dotenv.py
fastenv/py.typed
fastenv/types.py
fastenv/utilities.py
fastenv/cloud/__init__.py
fastenv/cloud/object_storage.py
fastenv-0.7.1.dist-info/METADATA
fastenv-0.7.1.dist-info/WHEEL
fastenv-0.7.1.dist-info/licenses/LICENSE
fastenv-0.7.1.dist-info/RECORD
