Metadata-Version: 2.4
Name: fastenv
Version: 0.7.1
Summary: Unified environment variable and settings management for FastAPI and beyond.
Project-URL: Documentation, https://fastenv.bws.bio
Project-URL: Homepage, https://github.com/br3ndonland/fastenv
Project-URL: Repository, https://github.com/br3ndonland/fastenv
Author-email: Brendon Smith <bws@bws.bio>
License-Expression: MIT
License-File: LICENSE
Keywords: asgi,dotenv,environment variables,fastapi,settings
Classifier: Environment :: Web Environment
Classifier: Intended Audience :: Developers
Classifier: Natural Language :: English
Classifier: Programming Language :: Python :: 3
Classifier: Programming Language :: Python :: 3.10
Classifier: Programming Language :: Python :: 3.11
Classifier: Programming Language :: Python :: 3.12
Classifier: Programming Language :: Python :: 3.13
Classifier: Topic :: Internet :: WWW/HTTP :: HTTP Servers
Classifier: Topic :: Software Development :: Libraries :: Application Frameworks
Classifier: Topic :: System :: Installation/Setup
Classifier: Topic :: System :: Systems Administration
Classifier: Topic :: Utilities
Classifier: Typing :: Typed
Requires-Python: <4,>=3.10
Requires-Dist: anyio<5,>=3.3
Provides-Extra: cloud
Requires-Dist: httpx<1,>=0.23; extra == 'cloud'
Provides-Extra: httpx
Requires-Dist: httpx<1,>=0.23; extra == 'httpx'
